priority_search_tree/__init__.py
priority_search_tree/print_helpers.py
priority_search_tree/ps_set.py
priority_search_tree/ps_tree.py
priority_search_tree/ps_tree_node.py
priority_search_tree-0.1.0.dist-info/AUTHORS.rst
priority_search_tree-0.1.0.dist-info/LICENSE
priority_search_tree-0.1.0.dist-info/METADATA
priority_search_tree-0.1.0.dist-info/WHEEL
priority_search_tree-0.1.0.dist-info/top_level.txt
priority_search_tree-0.1.0.dist-info/RECORD
