Metadata-Version: 2.1
Name: priority-search-tree
Version: 0.1.0
Summary: Priority search tree data structure
Home-page: https://github.com/yusinv/priority-search-tree
Author: Valentin Yusin
Author-email: yusinv@gmail.com
License: LGPL-3.0-or-later
Project-URL: Documentation, https://priority-search-tree.readthedocs.io/
Project-URL: Changelog, https://priority-search-tree.readthedocs.io/en/latest/changelog.html
Project-URL: Issue Tracker, https://github.com/yusinv/priority-search-tree/issues
Classifier: Development Status :: 3 - Alpha
Classifier: Intended Audience :: Developers
Classifier: Intended Audience :: Education
Classifier: License :: OSI Approved :: GNU Lesser General Public License v3 or later (LGPLv3+)
Classifier: Operating System :: Unix
Classifier: Operating System :: POSIX
Classifier: Operating System :: Microsoft :: Windows
Classifier: Programming Language :: Python
Classifier: Programming Language :: Python :: 3
Classifier: Programming Language :: Python :: 3 :: Only
Classifier: Programming Language :: Python :: 3.8
Classifier: Programming Language :: Python :: 3.9
Classifier: Programming Language :: Python :: 3.10
Classifier: Programming Language :: Python :: 3.11
Classifier: Programming Language :: Python :: 3.12
Classifier: Programming Language :: Python :: Implementation :: CPython
Classifier: Programming Language :: Python :: Implementation :: PyPy
Classifier: Topic :: Software Development :: Libraries
Requires-Python: >=3.8
License-File: LICENSE
License-File: AUTHORS.rst
